topyn/__init__.py
topyn/__main__.py
topyn/commands/__init__.py
topyn/commands/format.py
topyn/commands/rules.py
topyn/commands/types.py
topyn/configs/black.toml
topyn/configs/flake8.toml
topyn/configs/mypy.toml
topyn/configs/topyn.toml
topyn/console.py
topyn/tui.py
topyn-0.7.0.dist-info/entry_points.txt
topyn-0.7.0.dist-info/LICENSE
topyn-0.7.0.dist-info/WHEEL
topyn-0.7.0.dist-info/METADATA
topyn-0.7.0.dist-info/RECORD
