Metadata-Version: 2.1
Name: topyn
Version: 0.7.0
Summary: TOPyN: Typed Opinionated PYthon Normalizer
Home-page: https://github.com/lleites/topyn
License: MIT
Keywords: formatter,linter,style-guide,typing,opinionated
Author: Leandro Leites Barrios
Author-email: laloleites@gmail.com
Requires-Python: >=3.7,<4.0
Classifier: License :: OSI Approved :: MIT License
Classifier: Programming Language :: Python :: 3
Classifier: Programming Language :: Python :: 3.10
Classifier: Programming Language :: Python :: 3.7
Classifier: Programming Language :: Python :: 3.8
Classifier: Programming Language :: Python :: 3.9
Requires-Dist: autoflake (>=1.4.0,<1.5.0)
Requires-Dist: black (>=22.0.0,<23.0.0)
Requires-Dist: click (>=8.0.0,<9.0.0)
Requires-Dist: flake8 (>=4.0.0,<5.0.0)
Requires-Dist: flake8-bugbear
Requires-Dist: flake8-comprehensions
Requires-Dist: flake8-print
Requires-Dist: mypy
Requires-Dist: pep8-naming
Requires-Dist: toml
Project-URL: Repository, https://github.com/lleites/topyn
